tular/__init__.py
tular/adapters.py
tular/assets.py
tular/datatables.py
tular/interfaces.py
tular/maps.py
tular/models.py
tular/util.py
tular/views.py
tular/scripts/__init__.py
tular/scripts/initializedb.py
tular/static/Liberation_Sans-Regular.ttf.css
tular/static/PT_Sans-Caption-Web-Regular.ttf.css
tular/static/alignment.css
tular/static/alignment.js
tular/static/annodoc.js
tular/static/annotation_log.js
tular/static/config.js
tular/static/configuration.js
tular/static/conllu.js
tular/static/dispatcher.js
tular/static/jquery-ui.min.js
tular/static/jquery.min.js
tular/static/jquery.svg.min.js
tular/static/jquery.svgdom.min.js
tular/static/project.css
tular/static/project.js
tular/static/style-vis.css
tular/static/tupi1.png
tular/static/uni_tuebingen_logo.png
tular/static/url_monitor.js
tular/static/util.js
tular/static/visualizer.js
tular/static/waypoints.min.js
tular/static/webfont.js
tular/templates/completeness.mako
tular/templates/tular.mako
tular/templates/cognateset/detail_html.mako
tular/templates/contribution/detail_html.mako
tular/templates/dataset/detail_html.mako
tular/templates/language/detail_html.mako
tular/templates/language/index_html.mako
tular/templates/parameter/detail_html.mako
tular/templates/sentence/detail_html.mako
tular/templates/sentence/index_html.mako
tular/templates/valueset/detail_html.mako
tular-0.0.dist-info/LICENSE
tular-0.0.dist-info/METADATA
tular-0.0.dist-info/WHEEL
tular-0.0.dist-info/entry_points.txt
tular-0.0.dist-info/top_level.txt
tular-0.0.dist-info/RECORD
